pyreposync/__init__.py
pyreposync/downloader.py
pyreposync/exceptions.py
pyreposync/sync_deb822.py
pyreposync/sync_generic.py
pyreposync/sync_rpm.py
pyreposync-0.2.11.dist-info/METADATA
pyreposync-0.2.11.dist-info/WHEEL
pyreposync-0.2.11.dist-info/entry_points.txt
pyreposync-0.2.11.dist-info/licenses/LICENSE.txt
pyreposync-0.2.11.dist-info/RECORD
