Metadata-Version: 2.4
Name: pyreposync
Version: 0.2.11
Summary: rpm and deb822 repository sync tool
Project-URL: Source, https://github.com/schlitzered/pyreposync
Author-email: "Stephan.Schultchen" <sschultchen@gmail.com>
License: The MIT License (MIT)
License-File: LICENSE.txt
Classifier: Programming Language :: Python
Requires-Python: >=3.9
Requires-Dist: requests
